{
  "project": {
    "name": "logicn-app",
    "version": "0.1.0",
    "root": ".",
    "entryFiles": ["packages-logicn/logicn-framework-example-app/src/index.lln"],
    "packages": [
      "packages-logicn/logicn-core",
      "packages-logicn/logicn-core-config",
      "packages-logicn/logicn-framework-example-app"
    ],
    "production": {
      "packageOverrides": []
    },
    "strict": true,
    "targets": ["cpu", "wasm"],
    "defaultPackage": "packages-logicn/logicn-framework-example-app",
    "docs": {
      "app": "docs",
      "config": "packages-logicn/logicn-core-config"
    }
  },
  "environment": {
    "mode": "production",
    "variables": [
      {
        "name": "LogicN_APP_ENV",
        "required": true,
        "scope": "runtime"
      }
    ],
    "secrets": [
      {
        "name": "LogicN_APP_SECRET",
        "required": true,
        "scope": "runtime"
      }
    ]
  }
}
